SCSA/SCSA.py
SCSA/__init__.py
SCSA-0.1.9.dist-info/LICENSE.txt
SCSA-0.1.9.dist-info/METADATA
SCSA-0.1.9.dist-info/WHEEL
SCSA-0.1.9.dist-info/top_level.txt
SCSA-0.1.9.dist-info/RECORD
